Lab6/Part1/hdl/full_add_1_bit.v
module full_add_1_bit (a, b, c_in, sum, c_out);

  input a, b, c_in;
  output sum, c_out;

  assign {c_out, sum} = c_in + a + b;

endmodule

Lab6/Part3/hdl/full_add_8_bit.v
module full_add_8_bit(a, b, c_in, sum, c_out);

  input [7:0] a, b;
  input c_in;
  output [7:0] sum;
  output c_out;

  wire [7:0] c_internal;

  full_add_1_bit b0 (.a(a[0]), .b(b[0]), .c_in(c_in), .sum(sum[0]),
    .c_out(c_internal[0]));
  full_add_1_bit b1 (.a(a[1]), .b(b[1]), .c_in(c_internal[0]), .sum(sum[1]),
    .c_out(c_internal[1]));

  full_add_1_bit b2 (.a(a[2]), .b(b[2]), .c_in(c_internal[1]), .sum(sum[2]),
    .c_out(c_internal[2]));
  full_add_1_bit b3 (.a(a[3]), .b(b[3]), .c_in(c_internal[2]), .sum(sum[3]),
    .c_out(c_internal[3]));
  full_add_1_bit b4 (.a(a[4]), .b(b[4]), .c_in(c_internal[3]), .sum(sum[4]),
    .c_out(c_internal[4]));
  full_add_1_bit b5 (.a(a[5]), .b(b[5]), .c_in(c_internal[4]), .sum(sum[5]),
    .c_out(c_internal[5]));
  full_add_1_bit b6 (.a(a[6]), .b(b[6]), .c_in(c_internal[5]), .sum(sum[6]),
    .c_out(c_internal[6]));
  full_add_1_bit b7 (.a(a[7]), .b(b[7]), .c_in(c_internal[6]), .sum(sum[7]),
    .c_out(c_internal[7]));

  assign c_out = c_internal[7];

endmodule

Lab6/Part1/hdl/accumulator.v
module accumulator(clk, a, sum, v, c, reset_n);

  input [7:0] a;
  input clk, reset_n;
  output reg v, c; // v = overflow flag, c = carry flag
  output reg [7:0] sum;

  // internal signals
  wire [7:0] sum_d;
  wire v_d, c_d; // d as in data to DFF
  reg [7:0] a_q; // q as in output of DFF

  full_add_8_bit adder (.a(a), .b(sum), .c_in(1'b0), .sum(sum_d), .c_out(c_d));

  always @ (posedge clk or negedge reset_n)
  begin

    if (!reset_n)
    begin
      a_q <= 8'b0;
      sum <= 8'b0;
      c <= 1'b0;
      v <= 1'b0;
    end
    else
    begin
      a_q <= a;
      sum <= sum_d;
      c <= c_d;
      v <= v_d;
    end


  end

  assign v_d = (!(a_q[7] & sum[7]) | (a_q[7] & sum[7])) & sum_d[7];



endmodule

Lab6/Part1/testbenches/accumulator_tb.v
`timescale 1ns/1ns
`include "../hdl/accumulator.v"
`include "../hdl/full_add_8_bit.v"
`include "../hdl/full_add_1_bit.v"

module accumulator_tb();

  reg clk, reset_n;
  reg [7:0] a;
  wire v, c;
  wire [7:0] sum;

  accumulator acc (.clk(clk), .a(a), .sum(sum), .v(v), .c(c),
    .reset_n(reset_n));

  always begin
    clk = 1; #10; clk = 0; #10;
  end

  initial begin

    $dumpfile("acc.vcd");
    $dumpvars(0, accumulator_tb, acc);

    a = 8'b0; reset_n = 1'b0;
    #3;
    reset_n = 1'b1;
    #2;
    for (a=8'b0; a < 2**10; a=a+1'b1)
      #15 $display("a=%d", a);

  end

  initial begin
    #1000 $finish;
  end

endmodule

Lab6/Part1/testbenches/acc.vcd
$date
	Thu Jun 28 20:51:48 2018
$end
$version
	Icarus Verilog
$end
$timescale
	1ns
$end
$scope module accumulator_tb $end
$var wire 1 ! v $end
$var wire 8 " sum [7:0] $end
$var wire 1 # c $end
$var reg 8 $ a [7:0] $end
$var reg 1 % clk $end
$var reg 1 & reset_n $end
$scope module acc $end
$var wire 8 ' a [7:0] $end
$var wire 1 % clk $end
$var wire 1 & reset_n $end
$var wire 1 ( v_d $end
$var wire 8 ) sum_d [7:0] $end
$var wire 1 * c_d $end
$var reg 8 + a_q [7:0] $end
$var reg 1 # c $end
$var reg 8 , sum [7:0] $end
$var reg 1 ! v $end
$scope module adder $end
$var wire 8 - a [7:0] $end
$var wire 8 . b [7:0] $end
$var wire 1 / c_in $end
$var wire 8 0 sum [7:0] $end
$var wire 1 * c_out $end
$var wire 8 1 c_internal [7:0] $end
$scope module b0 $end
$var wire 1 2 a $end
$var wire 1 3 b $end
$var wire 1 / c_in $end
$var wire 1 4 sum $end
$var wire 1 5 c_out $end
$upscope $end
$scope module b1 $end
$var wire 1 6 a $end
$var wire 1 7 b $end
$var wire 1 8 c_in $end
$var wire 1 9 sum $end
$var wire 1 : c_out $end
$upscope $end
$scope module b2 $end
$var wire 1 ; a $end
$var wire 1 < b $end
$var wire 1 = c_in $end
$var wire 1 > sum $end
$var wire 1 ? c_out $end
$upscope $end
$scope module b3 $end
$var wire 1 @ a $end
$var wire 1 A b $end
$var wire 1 B c_in $end
$var wire 1 C sum $end
$var wire 1 D c_out $end
$upscope $end
$scope module b4 $end
$var wire 1 E a $end
$var wire 1 F b $end
$var wire 1 G c_in $end
$var wire 1 H sum $end
$var wire 1 I c_out $end
$upscope $end
$scope module b5 $end
$var wire 1 J a $end
$var wire 1 K b $end
$var wire 1 L c_in $end
$var wire 1 M sum $end
$var wire 1 N c_out $end
$upscope $end
$scope module b6 $end
$var wire 1 O a $end
$var wire 1 P b $end
$var wire 1 Q c_in $end
$var wire 1 R sum $end
$var wire 1 S c_out $end
$upscope $end
$scope module b7 $end
$var wire 1 T a $end
$var wire 1 U b $end
$var wire 1 V c_in $end
$var wire 1 W sum $end
$var wire 1 X c_out $end
$upscope $end
$upscope $end
$upscope $end
$upscope $end
$scope module accumulator_tb $end
$scope module acc $end
$scope module adder $end
$scope module b0 $end
$upscope $end
$scope module b1 $end
$upscope $end
$scope module b2 $end
$upscope $end
$scope module b3 $end
$upscope $end
$scope module b4 $end
$upscope $end
$scope module b5 $end
$upscope $end
$scope module b6 $end
$upscope $end
$scope module b7 $end
$upscope $end
$upscope $end
$upscope $end
$upscope $end
$enddefinitions $end
#0
$dumpvars
0X
0W
0V
0U
0T
0S
0R
0Q
0P
0O
0N
0M
0L
0K
0J
0I
0H
0G
0F
0E
0D
0C
0B
0A
0@
0?
0>
0=
0<
0;
0:
09
08
07
06
05
04
03
02
b0 1
b0 0
0/
b0 .
b0 -
b0 ,
b0 +
0*
b0 )
0(
b0 '
0&
1%
b0 $
0#
b0 "
0!
$end
#3
1&
#10
0%
#20
b1 +
b1 )
b1 0
14
12
1%
b1 $
b1 '
b1 -
#30
0%
#35
04
b10 )
b10 0
19
02
16
b10 $
b10 '
b10 -
#40
1>
1=
b100 )
b100 0
09
b10 1
1:
17
b10 "
b10 ,
b10 .
b10 +
1%
#50
b101 )
b101 0
14
12
0%
b11 $
b11 '
b11 -
#60
1C
18
1=
1B
04
15
09
1:
b1000 )
b1000 0
0>
b111 1
1?
13
07
1<
b101 "
b101 ,
b101 .
b11 +
1%
#65
08
0=
14
05
09
b100 1
0:
b1001 )
b1001 0
0>
02
06
1;
b100 $
b100 '
b100 -
#70
0%
#80
0H
0B
0G
1>
0?
1C
0D
0<
1A
b1001 "
b1001 ,
b1001 .
b101 +
19
18
b1110 )
b1110 0
04
b1 1
15
12
1%
b101 $
b101 '
b101 -
#90
0%
#95
0H
0G
1C
0D
0B
1>
0?
08
0=
14
05
b1111 )
b1111 0
19
b0 1
0:
02
16
b110 $
b110 '
b110 -
#100
1H
1G
0C
1D
1=
1B
09
1:
b10101 )
b10101 0
1>
b1110 1
1?
17
1<
b1111 "
b1111 ,
b1111 .
b110 +
1%
#110
19
18
b10110 )
b10110 0
04
b1111 1
15
12
0%
b111 $
b111 '
b111 -
#120
09
0M
08
0G
0L
14
05
1C
0D
b11101 )
b11101 0
1H
b110 1
0I
03
0A
1F
b10110 "
b10110 ,
b10110 .
b111 +
1%
#125
0M
0B
0L
0?
1H
0I
0=
0G
04
19
0:
1>
b11110 )
b11110 0
1C
b0 1
0D
02
06
0;
1@
b1000 $
b1000 '
b1000 -
#130
0%
#140
1M
1L
0H
1I
1G
0C
b11000 1
1D
1A
b11110 "
b11110 ,
b11110 .
b1001 +
b100111 )
b100111 0
14
12
1%
b1001 $
b1001 '
b1001 -
#150
0%
#155
1C
1B
0>
1?
1=
04
b101000 )
b101000 0
09
b11110 1
1:
02
16
b1010 $
b1010 '
b1010 -
#160
0C
0R
0=
0B
0L
0Q
19
0:
0>
0?
1H
0I
b110010 )
b110010 0
1M
b1000 1
0N
07
0<
0F
1K
b101000 "
b101000 ,
b101000 .
b1010 +
1%
#170
b110011 )
b110011 0
14
12
0%
b1011 $
b1011 '
b1011 -
#180
0R
0Q
1>
1M
0N
18
1=
0G
0L
04
15
19
1:
1C
0D
b111110 )
b111110 0
1H
b11 1
0I
13
17
0A
1F
b110011 "
b110011 ,
b110011 .
b1011 +
1%
#185
0R
0Q
1M
0N
0L
1H
0I
0=
0G
0:
1C
0D
08
0B
14
05
19
b111111 )
b111111 0
1>
b0 1
0?
02
06
1;
b1100 $
b1100 '
b1100 -
#190
0%
#200
1<
1A
b111111 "
b111111 ,
b111111 .
b1101 +
1R
1Q
0M
1N
1L
0H
1I
1G
1C
1D
1B
1>
1?
1=
09
1:
18
b1001100 )
b1001100 0
04
b111111 1
15
12
1%
b1101 $
b1101 '
b1101 -
#210
0%
#215
08
14
b111110 1
05
b1001101 )
b1001101 0
09
02
16
b1110 $
b1110 '
b1110 -
#220
0(
0>
0W
0=
0L
0Q
0V
19
0:
1H
0I
0M
0N
b1011011 )
b1011011 0
1R
b1100 1
0S
07
0F
0K
1P
b1001101 "
b1001101 ,
b1001101 .
b1110 +
1%
#230
1>
1=
09
1:
18
b1011100 )
b1011100 0
04
b1111 1
15
12
0%
b1111 $
b1111 '
b1111 -
#240
0>
0=
19
0:
1M
08
1L
14
05
b1101011 )
b1101011 0
0H
b11100 1
1I
03
1F
b1011100 "
b1011100 ,
b1011100 .
b1111 +
1%
#245
0G
0D
0B
04
09
1>
b10000 1
0?
1C
b1101100 )
b1101100 0
0H
02
06
0;
0@
1E
b10000 $
b10000 '
b10000 -
#250
0%
#260
0(
0W
0V
1R
0S
0L
0Q
1H
0I
1M
b0 1
0N
0F
1K
b1101100 "
b1101100 ,
b1101100 .
b10001 +
b1111101 )
b1111101 0
14
12
1%
b10001 $
b10001 '
b10001 -
#270
0%
#275
04
b1111110 )
b1111110 0
19
02
16
b10010 $
b10010 '
b10010 -
#280
1(
1W
1G
1V
0C
1D
0R
1S
1B
1Q
0>
1?
0M
1N
1=
1L
09
1:
b10010000 )
b10010000 0
1H
b1111110 1
1I
17
1F
b1111110 "
b1111110 ,
b1111110 .
b10010 +
1%
#290
b10010001 )
b10010001 0
14
12
0%
b10011 $
b10011 '
b10011 -
#300
0H
1(
18
1=
0B
0G
0Q
0V
0*
04
15
09
1:
1>
0?
0C
0D
1M
0N
0R
0S
b10100100 )
b10100100 0
1W
b10011 1
0X
13
07
0<
0A
0K
0P
1U
1!
b10010001 "
b10010001 ,
b10010001 .
b10011 +
1%
#305
0C
08
0=
0B
14
05
09
0:
b10100101 )
b10100101 0
1>
b10000 1
0?
02
06
1;
b10100 $
b10100 '
b10100 -
#310
0%
#320
1C
0R
1B
0L
0Q
0>
1?
1H
0I
1M
0N
1<
0F
1K
b10100101 "
b10100101 ,
b10100101 .
b10101 +
19
18
b10111010 )
b10111010 0
04
b101 1
15
12
1%
b10101 $
b10101 '
b10101 -
#330
0%
#335
0>
08
0=
14
05
b10111011 )
b10111011 0
19
b100 1
0:
02
16
b10110 $
b10110 '
b10110 -
#340
1R
1Q
0M
1N
1=
1B
1G
1L
09
1:
0>
1?
0C
1D
b11010001 )
b11010001 0
1H
b111110 1
1I
17
0<
1A
1F
b10111011 "
b10111011 ,
b10111011 .
b10110 +
1%
#350
19
18
b11010010 )
b11010010 0
04
b111111 1
15
12
0%
b10111 $
b10111 '
b10111 -
#360
1(
0*
09
0H
1W
0X
08
0G
0Q
0V
14
05
1C
0D
1M
0N
b11101001 )
b11101001 0
1R
b10110 1
0S
03
0A
0K
1P
b11010010 "
b11010010 ,
b11010010 .
b10111 +
1%
#365
0H
0=
0B
0G
04
19
0:
0>
0?
b11101010 )
b11101010 0
1C
b10000 1
0D
02
06
0;
1@
b11000 $
b11000 '
b11000 -
#370
0%
#380
0(
1*
0W
1X
1V
0R
1S
1G
1L
1Q
0C
1D
0H
1I
0M
b11111000 1
1N
1A
0F
1K
b11101010 "
b11101010 ,
b11101010 .
b11001 +
b11 )
b11 0
14
12
1%
b11001 $
b11001 '
b11001 -
#390
0%
#395
1>
1=
04
b100 )
b100 0
09
b11111010 1
1:
02
16
b11010 $
b11010 '
b11010 -
#400
0L
1H
0I
0(
0=
0B
0G
0Q
0V
0*
19
0:
1>
0?
1C
0D
0M
0N
0R
0S
b11110 )
b11110 0
0W
b0 1
0X
07
1<
0A
0K
0P
0U
0!
1#
b100 "
b100 ,
b100 .
b11010 +
1%
#410
b11111 )
b11111 0
14
12
0%
b11011 $
b11011 '
b11011 -
#420
1B
0>
1?
1M
18
1=
1G
1L
04
15
19
1:
1C
1D
b111010 )
b111010 0
1H
b11111 1
1I
13
17
1A
1F
0#
b11111 "
b11111 ,
b11111 .
b11011 +
1%
#425
0=
0:
08
14
b11100 1
05
19
b111011 )
b111011 0
0>
02
06
1;
b11100 $
b11100 '
b11100 -
#430
0%
#440
1R
1Q
0M
1N
0<
1K
b111011 "
b111011 ,
b111011 .
b11101 +
0>
1=
09
1:
18
b1011000 )
b1011000 0
04
b111111 1
15
12
1%
b11101 $
b11101 '
b11101 -
#450
0%
#455
08
14
b111110 1
05
b1011001 )
b1011001 0
09
02
16
b11110 $
b11110 '
b11110 -
#460
0C
0(
0B
1>
0?
0W
0=
0Q
0V
19
0:
1M
0N
b1110111 )
b1110111 0
1R
b11000 1
0S
07
0K
1P
b1011001 "
b1011001 ,
b1011001 .
b11110 +
1%
#470
1C
1B
0>
1?
1=
09
1:
18
b1111000 )
b1111000 0
04
b11111 1
15
12
0%
b11111 $
b11111 '
b11111 -
#480
0C
1(
0B
1>
0?
1W
0=
1V
19
0:
0R
1S
08
1Q
14
05
b10010111 )
b10010111 0
0M
b1111000 1
1N
03
1K
b1111000 "
b1111000 ,
b1111000 .
b11111 +
1%
#485
0L
0I
0G
04
09
0>
1C
b1100000 1
0D
1H
b10011000 )
b10011000 0
0M
02
06
0;
0@
0E
1J
b100000 $
b100000 '
b100000 -
#490
0%
#500
1(
0Q
0V
0*
1M
0N
0R
0S
1W
b0 1
0X
0K
0P
1U
1!
b10011000 "
b10011000 ,
b10011000 .
b100001 +
b10111001 )
b10111001 0
14
12
1%
b100001 $
b100001 '
b100001 -
#510
0%
#515
04
b10111010 )
b10111010 0
19
02
16
b100010 $
b100010 '
b100010 -
#520
1>
1R
1=
1Q
09
1:
b11011100 )
b11011100 0
0M
b100010 1
1N
17
1K
b10111010 "
b10111010 ,
b10111010 .
b100010 +
1%
#530
b11011101 )
b11011101 0
14
12
0%
b100011 $
b100011 '
b100011 -
#540
1L
0H
1I
0(
1G
1*
0C
1D
0W
1X
18
1=
1B
1Q
1V
04
15
09
1:
0>
1?
0M
1N
b0 )
b0 0
0R
b11111111 1
1S
13
07
1<
0K
1P
b11011101 "
b11011101 ,
b11011101 .
b100011 +
1%
#545
08
0=
14
05
09
b11111100 1
0:
b1 )
b1 0
0>
02
06
1;
b100100 $
b100100 '
b100100 -
#550
0%
#560
0Q
1M
0N
0(
0B
0G
0L
0V
0*
1>
0?
0C
0D
0H
0I
0R
0S
0W
0X
0<
0A
0F
0P
0U
0!
1#
b1 "
b1 ,
b1 .
b100101 +
19
18
b100110 )
b100110 0
04
b1 1
15
12
1%
b100101 $
b100101 '
b100101 -
#570
0%
#575
0C
0B
1>
0?
08
0=
14
05
b100111 )
b100111 0
19
b0 1
0:
02
16
b100110 $
b100110 '
b100110 -
#580
1C
1R
1=
1B
1Q
09
1:
1>
1?
b1001101 )
b1001101 0
0M
b100110 1
1N
17
1<
1K
0#
b100111 "
b100111 ,
b100111 .
b100110 +
1%
#590
19
18
b1001110 )
b1001110 0
04
b100111 1
15
12
0%
b100111 $
b100111 '
b100111 -
#600
0(
09
1H
0W
08
1G
0Q
0V
14
05
0C
1D
1M
0N
b1110101 )
b1110101 0
1R
b1110 1
0S
03
1A
0K
1P
b1001110 "
b1001110 ,
b1001110 .
b100111 +
1%
#605
0B
0?
0=
04
19
b1000 1
0:
1>
b1110110 )
b1110110 0
0C
02
06
0;
1@
b101000 $
b101000 '
b101000 -
#610
0%
#620
1(
1W
1V
0R
1S
0G
0L
1Q
1C
0D
1H
0I
0M
b1100000 1
1N
0A
1F
1K
b1110110 "
b1110110 ,
b1110110 .
b101001 +
b10011111 )
b10011111 0
14
12
1%
b101001 $
b101001 '
b101001 -
#630
0%
#635
1M
1L
0H
1I
1G
0C
1D
1B
0>
1?
1=
04
b10100000 )
b10100000 0
09
b1111110 1
1:
02
16
b101010 $
b101010 '
b101010 -
#640
0G
1C
0D
0M
1(
0=
0B
0L
0V
0*
19
0:
0>
0?
0H
0I
1R
0S
b11001010 )
b11001010 0
1W
b100000 1
0X
07
0<
0F
0P
1U
1!
b10100000 "
b10100000 ,
b10100000 .
b101010 +
1%
#650
b11001011 )
b11001011 0
14
12
0%
b101011 $
b101011 '
b101011 -
#660
1(
0*
1>
1H
1W
0X
18
1=
1G
0Q
0V
04
15
19
1:
0C
1D
1M
0N
b11110110 )
b11110110 0
1R
b1011 1
0S
13
17
1A
0K
1P
b11001011 "
b11001011 ,
b11001011 .
b101011 +
1%
#665
0=
0:
0C
08
0B
14
05
19
b11110111 )
b11110111 0
1>
b1000 1
0?
02
06
1;
b101100 $
b101100 '
b101100 -
#670
0%
#680
0(
1*
0W
1X
1V
0R
1S
1L
1Q
0H
1I
1M
1N
1<
0A
1F
1K
b11110111 "
b11110111 ,
b11110111 .
b101101 +
0C
1B
1>
1?
1=
09
1:
18
b100100 )
b100100 0
04
b11111111 1
15
12
1%
b101101 $
b101101 '
b101101 -
#690
0%
#695
08
14
b11111110 1
05
b100101 )
b100101 0
09
02
16
b101110 $
b101110 '
b101110 -
#700
0>
0M
0(
0=
0L
0V
0*
19
0:
1H
0I
1R
0S
b1010011 )
b1010011 0
0W
b101100 1
0X
07
0F
0P
0U
0!
1#
b100101 "
b100101 ,
b100101 .
b101110 +
1%
#710
1>
1=
09
1:
18
b1010100 )
b1010100 0
04
b101111 1
15
12
0%
b101111 $
b101111 '
b101111 -
#720
0>
1(
0=
19
0:
1W
08
1L
1Q
1V
14
05
0H
1I
0M
1N
b10000011 )
b10000011 0
0R
b1111100 1
1S
03
1F
0K
1P
0#
b1010100 "
b1010100 ,
b1010100 .
b101111 +
1%
#725
0B
0G
04
09
1>
0?
0C
b1110000 1
0D
b10000100 )
b10000100 0
0H
02
06
0;
0@
1E
b110000 $
b110000 '
b110000 -
#730
0%
#740
0Q
1M
0N
1(
0L
0V
0*
1H
0I
0R
0S
1W
b0 1
0X
0F
0P
1U
1!
b10000100 "
b10000100 ,
b10000100 .
b110001 +
b10110101 )
b10110101 0
14
12
1%
b110001 $
b110001 '
b110001 -
#750
0%
#755
04
b10110110 )
b10110110 0
19
02
16
b110010 $
b110010 '
b110010 -
#760
1C
1B
0>
1?
1R
1=
1L
1Q
09
1:
0H
1I
b11101000 )
b11101000 0
1M
b110110 1
1N
17
1F
1K
b10110110 "
b10110110 ,
b10110110 .
b110010 +
1%
#770
b11101001 )
b11101001 0
14
12
0%
b110011 $
b110011 '
b110011 -
#780
0(
1*
0M
0W
1X
18
1=
0B
0G
0L
1V
04
15
09
1:
1>
0?
1C
0D
1H
0I
b11100 )
b11100 0
0R
b11100011 1
1S
13
07
0<
1A
0F
1P
b11101001 "
b11101001 ,
b11101001 .
b110011 +
1%
#785
0M
0L
1H
0I
0G
1C
0D
08
0=
0B
14
05
09
0:
b11101 )
b11101 0
1>
b11100000 1
0?
02
06
1;
b110100 $
b110100 '
b110100 -
#790
0%
#800
1G
0C
1D
0(
1B
1L
1Q
0V
0*
0>
1?
1H
1I
0M
1N
1R
0S
0W
0X
1<
1F
0K
0P
0U
0!
1#
b11101 "
b11101 ,
b11101 .
b110101 +
19
18
b1010010 )
b1010010 0
04
b111101 1
15
12
1%
b110101 $
b110101 '
b110101 -
#810
0%
#815
0>
08
0=
14
05
b1010011 )
b1010011 0
19
b111100 1
0:
02
16
b110110 $
b110110 '
b110110 -
#820
1(
0H
1W
1=
1B
0G
1V
09
1:
0>
1?
1C
0D
b10001001 )
b10001001 0
0R
b1110110 1
1S
17
0<
0A
1P
0#
b1010011 "
b1010011 ,
b1010011 .
b110110 +
1%
#830
19
18
b10001010 )
b10001010 0
04
b1110111 1
15
12
0%
b110111 $
b110111 '
b110111 -
#840
1Q
09
0M
1N
1(
08
1G
1L
0V
0*
14
05
0C
1D
0H
1I
1R
0S
b11000001 )
b11000001 0
1W
b111110 1
0X
03
1A
0F
0P
1U
1!
b10001010 "
b10001010 ,
b10001010 .
b110111 +
1%
#845
0=
0B
04
19
0:
0>
b111000 1
0?
b11000010 )
b11000010 0
0C
02
06
0;
1@
b111000 $
b111000 '
b111000 -
#850
0%
#860
0Q
1M
0N
1(
0L
0*
1H
0I
1W
0X
0G
0V
1C
0D
1R
b0 1
0S
0A
1P
b11000010 "
b11000010 ,
b11000010 .
b111001 +
b11111011 )
b11111011 0
14
12
1%
b111001 $
b111001 '
b111001 -
#870
0%
#875
1>
1=
04
b11111100 )
b11111100 0
09
b10 1
1:
02
16
b111010 $
b111010 '
b111010 -
#880
0(
1*
0W
1X
1V
0R
1S
0=
0B
1G
1L
1Q
19
0:
1>
0?
0C
1D
1H
1I
b110110 )
b110110 0
1M
b11111000 1
1N
07
1<
1A
1F
1K
b11111100 "
b11111100 ,
b11111100 .
b111010 +
1%
#890
b110111 )
b110111 0
14
12
0%
b111011 $
b111011 '
b111011 -
#900
1B
0>
1?
1H
0(
18
1=
1G
0V
0*
04
15
19
1:
0C
1D
1R
0S
b1110010 )
b1110010 0
0W
b111111 1
0X
13
17
0A
0P
0U
0!
1#
b110111 "
b110111 ,
b110111 .
b111011 +
1%
#905
0=
0:
08
14
b111100 1
05
19
b1110011 )
b1110011 0
0>
02
06
1;
b111100 $
b111100 '
b111100 -
#910
0%
#920
1(
1W
1V
0R
1S
0<
1P
0#
b1110011 "
b1110011 ,
b1110011 .
b111101 +
0>
1=
09
1:
18
b10110000 )
b10110000 0
04
b1111111 1
15
12
1%
b111101 $
b111101 '
b111101 -
#930
0%
#935
08
14
b1111110 1
05
b10110001 )
b10110001 0
09
02
16
b111110 $
b111110 '
b111110 -
#940
0H
0G
1C
0D
0B
1>
0?
1(
0=
0V
0*
19
0:
1R
0S
b11101111 )
b11101111 0
1W
b110000 1
0X
07
0P
1U
1!
b10110001 "
b10110001 ,
b10110001 .
b111110 +
1%
#950
1H
1G
0C
1D
1B
0>
1?
1=
09
1:
18
b11110000 )
b11110000 0
04
b111111 1
15
12
0%
b111111 $
b111111 '
b111111 -
#960
0H
0G
1C
0D
0B
1>
0?
0(
0=
1*
19
0:
0W
1X
08
1V
14
05
b101111 )
b101111 0
0R
b11110000 1
1S
03
1P
b11110000 "
b11110000 ,
b11110000 .
b111111 +
1%
#965
0Q
0N
0L
04
09
0>
0C
1H
b11000000 1
0I
1M
b110000 )
b110000 0
0R
02
06
0;
0@
0E
0J
1O
b1000000 $
b1000000 '
b1000000 -
#970
0%
#980
0(
0V
0*
1R
0S
0W
b0 1
0X
0P
0U
0!
1#
b110000 "
b110000 ,
b110000 .
b1000001 +
b1110001 )
b1110001 0
14
12
1%
b1000001 $
b1000001 '
b1000001 -
#990
0%
#995
04
b1110010 )
b1110010 0
19
02
16
b1000010 $
b1000010 '
b1000010 -
#1000
1(
1>
1W
1=
1V
09
1:
b10110100 )
b10110100 0
0R
b1000010 1
1S
17
1P
0#
b1110010 "
b1110010 ,
b1110010 .
b1000010 +
1%
