Lab5/Part1/hdl/modulo_counter.v
module modulo_counter (clk, reset_n, q, rollover);

  parameter n = 4;
  parameter k = 8;

  input clk, reset_n;
  output reg [n-1:0] q;
  output reg rollover;

  always @ (posedge clk or negedge reset_n)
  begin

    if (!reset_n)
    begin
      q <= 0;
      rollover <= 0;
    end

    else if (q == k-1)
    begin
      q <= 1'd0;
      rollover <= 1;
    end

    else
    begin
      q <= q + 1'b1;
      rollover <= 0;
    end
  end

endmodule

Lab5/Part4/hdl/display_logic_new.v
module display_logic_new(clk, count2_in, size_in, sym_in, reset_n, disp_n, //half_sec_in,
  ld_out, en_reg_out, en_count_out, reset_count_out, led_out, //);
  debug_all_syms_procd, debug_size_in, debug_size_count, debug_count2_in, debug_sym_in);

  input clk, sym_in, disp_n, reset_n; //TODO: maybe don't need reset?
  input [2:0] size_in;
  input [1:0] count2_in;
  output ld_out;
  output reg en_reg_out, en_count_out, reset_count_out, led_out;
  //debug outputs
  output reg debug_all_syms_procd;
  output [2:0] debug_size_in, debug_size_count;
  output [1:0] debug_count2_in;
  output debug_sym_in;

  //internal signals
  //reg [1:0] array_1or3; // hold LED for either 1 or 3 pulses
  reg [2:0] size_counter;
  reg led_off_for_one_pulse;
  wire [1:0] array_1or3;

  always @ (posedge clk or negedge reset_n)
  begin

    if (!reset_n)
    begin
      en_reg_out <= 1'b0;
      en_count_out <= 1'b0;
      reset_count_out <= ~(1'b1);
      led_out <= 1'b0;

      size_counter <= 3'd0;
      led_off_for_one_pulse <= 1'b0;
      //debug signals
      debug_all_syms_procd <= 1'b0;
    end

    else if (~disp_n) // start displaying!
    begin
      //en_reg_out <= 1'b1;
      en_count_out <= 1'b1;
      reset_count_out <= ~(1'b1);
      led_out <= 1'b1;

      size_counter <= 3'd0;
      //size_counter <= 3'd1;
      led_off_for_one_pulse <= 1'b0;
    end

    else if ((led_off_for_one_pulse == 1'b1) && (count2_in == 2'b1) && (size_in != size_counter)) // if going blank for a bit;
    begin

      led_off_for_one_pulse <= 1'b0;
      led_out <= 1'b1;
      reset_count_out <= ~(1'b1); //TODO: Necessary?
      en_count_out <= 1'b1; //TODO: Necessary?
      //size_counter <= size_counter + 1'b1; //TODO: Placement?

      //debug
      //debug_all_syms_procd <= 1'b1; //TODO: DELETE
    end

    //else if (count2_in == size_in) // if one sym has been processed
    //else if (sym_in == array_1or3) // if one sym has been proc'd
    else if (count2_in == array_1or3) // if one sym has been proc'd
    begin

      led_out <= 0;
      //size_counter <= size_counter + 1'b1; // TODO: Placement?
      //if (size_in == size_counter - 1'b1) //if all syms of letter are processed
      if (size_in == size_counter) //if all syms of letter are processed
      begin
        en_reg_out <= 1'b0;
        en_count_out <= 1'b0;
        reset_count_out <= ~(1'b1);

        // debug
        debug_all_syms_procd <= 1'b1; //TODO: Uncomment this
        //debug_all_syms_procd <= 1'b0; //TODO: Delete this
        //size_counter <= 3'd0;
      end

      else // there are still some syms left to process
      begin
        //if (en_reg_out == 1'b0) // to account for that bullshit that was happening that I documented
        //begin
          en_reg_out <= 1'b1; // shift the next symbol out
          reset_count_out <= ~(1'b1); //should force count2_in to 0
          //en_count_out <= 1'b0;

          size_counter <= size_counter + 1'b1;
          led_off_for_one_pulse <= 1'b1;
          //debug_all_syms_procd <= 1'b0; //TODO: DELETE
        //end
        /*else //en_reg_out == 1'b1
        begin
          en_reg_out <= 1'b0;
          reset_count_out <= ~(1'b0); //should force count2_in to 0
          en_count_out <= 1'b1;
        end*/
      end
    end

    else
    begin
        en_reg_out <= 1'b0;
        reset_count_out <= ~(1'b0); //it's okay that 1to3 counter keeps going
    end
  end

  // combo logic
  assign ld_out = ~disp_n; // load values into letter size and letter symbol registers
  assign array_1or3 = (sym_in == 1'b0) ? 2'd1 : 2'd3;

  // debug
  //assign debug_size_in = size_in; // 9:7
  assign debug_size_in = count2_in; // 9:7
  assign debug_size_count = size_counter; //6:4
  assign debug_count2_in = array_1or3; //3:2
  assign debug_sym_in = sym_in; //1
  //assign debug_sym_in = debug_all_syms_procd; //1
  //assign debug_sym_in = en_count_out; //1
  //assign debug_count2_in = count2_in; //2:1 (works)

endmodule

Lab5/Part4/hdl/letter_sym_sr.v
// implementation inspired by:
// https://courses.cs.washington.edu/courses/cse467/05wi/pdfs/lectures/07-SequentialVerilog.pdf

// parallel in, serial out

// input: 0 for 0.5 s, 1 for 1.5 s
module letter_sym_sr(d, clk, reset_n, en, ld, q);

  input         clk, reset_n, en, ld;
  input [3:0]   d;
  output        q;

  // internal signals
  reg [3:0]     sr;

  always @ (posedge clk or negedge reset_n)
  begin

    if (!reset_n)
      //q = 1'b0; TODO: 10137 HDL Procedural Assignment error: object "q" on LHS of assignment must have variable data types
		sr = 4'b0000;

    else if (ld)
      sr = d;

    else if (en)
      sr = {sr[2:0], 1'b0};

  end

  assign q = sr[3];


endmodule

Lab5/Part4/hdl/letter_size_reg.v
//module letter_size_reg(d, clk, reset_n, en, ld, q);

// removed en
module letter_size_reg(d, clk, reset_n, ld, q);

  //input           clk, reset_n, en, ld;
  input           clk, reset_n, ld; //TODO: Don't need enable signal for this register anymore, right?
  input   [2:0]   d;
  output reg [2:0]   q;

  always @ (posedge clk or negedge reset_n)
  begin

    if (!reset_n)
      q = 3'b000;
    else if (ld)
      q = d;

  end

endmodule

Lab5/Part4/hdl/letter_sel_logic.v
//dot = 0; dash = 1; don't care = 0, enumerated X

module letter_sel_logic(letter_in, size, letter_out);

  input [2:0] letter_in;
  output reg  [2:0] size;
  output reg [3:0] letter_out;

  always @ (letter_in)
  begin

    case (letter_in)

      3'b000: begin // A
        size <= 3'd2;
        letter_out <= 4'b0100; // * _ X X
      end
      3'b001: begin // B
        size <= 3'd4;
        letter_out <= 4'b1000; // _ * * *
      end
      3'b010: begin // C
        size <= 3'd4;
        letter_out <= 4'b1010; // _ * _ *
      end
      3'b011: begin // D
        size <= 3'd3;
        letter_out <= 4'b1000;// _ * * X
      end
      3'b100: begin // E
        size <= 3'd1;
        letter_out <= 4'b0000; // * X X X
      end
      3'b101: begin // F
        size <= 3'd4;
        letter_out <= 4'b0010; // * * _ *
      end
      3'b110: begin // G
        size <= 3'd3;
        letter_out <= 4'b1100; // _ _ * X
      end
      3'b111: begin // H
        size <= 3'd4;
        letter_out <= 4'b0000; // * * * * 
      end

    endcase

  end

endmodule

Lab5/Part4/hdl/morse_a_h_top.v
module morse_a_h_top(KEY, CLOCK_50, SW, LEDR);

	input CLOCK_50;
	input [1:0] KEY;
	input [2:0] SW;
	output [9:0]LEDR;

	// internal signals
	wire [3:0] letter;
	wire ld_reg_from_disp;
	wire [2:0] size;
	wire [2:0] size_from_reg;
	wire sr_q, en_reg_from_disp, en_count_from_disp, reset_from_disp;
	wire key0_AND_reset_from_disp;

	//for display_logic_new
	wire [1:0] count2_in;

	//debug
	//wire debug_all_syms_procd; LEDR[8]

	//reg dummy;

	/*always @ (posedge CLOCK_50)
	begin
		if (half_sec_sig)
			dummy <= ~dummy;
	end*/

	letter_sel_logic letter_logic (.letter_in(SW), .size(size), .letter_out(letter));

	letter_size_reg size_reg (.d(size), .clk(CLOCK_50), .reset_n(KEY[0]),
		.ld(ld_reg_from_disp), .q(size_from_reg));
	letter_sym_sr shift_reg (.d(letter), .clk(CLOCK_50), .reset_n(KEY[0]),
		.en(en_reg_from_disp), .ld(ld_reg_from_disp), .q(sr_q));

	display_logic_new disp (.clk(CLOCK_50), .count2_in(count2_in),
		.size_in(size_from_reg), .sym_in(sr_q), .reset_n(KEY[0]), .disp_n(KEY[1]),
		.ld_out(ld_reg_from_disp), .en_reg_out(en_reg_from_disp),
		.en_count_out(en_count_from_disp), .reset_count_out(reset_from_disp),
		.led_out(LEDR[0]), //); start debug
		.debug_all_syms_procd(),//LEDR[9]),
		.debug_size_in(LEDR[9:7]),
		.debug_size_count(LEDR[6:4]),//3]),
		.debug_count2_in(LEDR[3:2]),
		.debug_sym_in(LEDR[1]));

	modulo_counter half_sec (.clk(CLOCK_50 && en_count_from_disp), .reset_n(key0_AND_reset_from_disp), .q(),
  	.rollover(half_sec_sig));
    defparam half_sec.n = 25;
	  //defparam half_sec.k = 25'b1011111010111100001000000;
		defparam half_sec.k = 25'b10000;

	modulo_counter count_1or3 (.clk(half_sec_sig && en_count_from_disp), .reset_n(key0_AND_reset_from_disp),
		.q(count2_in), .rollover());
	  defparam count_1or3.n = 2;
	  defparam count_1or3.k = 4; //TODO: change back to 3? Yup, I needed to. It was never getting to 3, and this's
																// the thing that will satisfy count2_in == array_1or3

	assign key0_AND_reset_from_disp = KEY[0] & reset_from_disp;
	//debug
	//assign LEDR[1] = dummy;

	endmodule

Lab5/Part4/testbenches/morse_tb.v
`timescale 1ns/1ns
`include "../../Part1/hdl/modulo_counter.v"
`include "../hdl/display_logic_new.v"
`include "../hdl/letter_sel_logic.v"
`include "../hdl/letter_size_reg.v"
`include "../hdl/letter_sym_sr.v"
`include "../hdl/morse_a_h_top.v"

module morse_tb();

  reg CLOCK_50;
  reg [1:0] KEY; //KEY[0] = reset; KEY[1] = load
  reg [2:0] SW;

  morse_a_h_top dut (.KEY(KEY),
                .CLOCK_50(CLOCK_50),
                .SW(SW),
                .LEDR()
                );

  // generate clock
  always begin
    CLOCK_50 = 1; #10; CLOCK_50 = 0; #10; // 20 ns period (50MHz CLK)
  end

  initial begin

    $dumpfile("anthony.vcd");
    $dumpvars(0, morse_tb);

    KEY = 2'b11; SW = 3'b0;
    #2; // 2ns
    KEY[0] = 1'b0; //Press RESET
    #20; //22 ns
    KEY[0] = 1'b1; // Release RESET
    #20; //42 ns
    KEY[1] = 1'b0; // Press LOAD
    #20; //64 ns
    KEY[1] = 1'b1; // Release LOAD
  end

  initial begin
    #1000000 $finish;
  end

endmodule

Lab5/Part4/testbenches/anthony.vcd
$date
	Mon Jun 25 21:23:54 2018
$end
$version
	Icarus Verilog
$end
$timescale
	1ns
$end
$scope module morse_tb $end
$var reg 1 ! CLOCK_50 $end
$var reg 2 " KEY [1:0] $end
$var reg 3 # SW [2:0] $end
$scope module dut $end
$var wire 1 ! CLOCK_50 $end
$var wire 2 $ KEY [1:0] $end
$var wire 3 % SW [2:0] $end
$var wire 1 & key0_AND_reset_from_disp $end
$var wire 1 ' sr_q $end
$var wire 3 ( size_from_reg [2:0] $end
$var wire 3 ) size [2:0] $end
$var wire 1 * reset_from_disp $end
$var wire 4 + letter [3:0] $end
$var wire 1 , ld_reg_from_disp $end
$var wire 1 - half_sec_sig $end
$var wire 1 . en_reg_from_disp $end
$var wire 1 / en_count_from_disp $end
$var wire 2 0 count2_in [1:0] $end
$var wire 10 1 LEDR [9:0] $end
$scope module count_1or3 $end
$var wire 1 2 clk $end
$var wire 1 & reset_n $end
$var reg 2 3 q [1:0] $end
$var reg 1 4 rollover $end
$upscope $end
$scope module disp $end
$var wire 1 ! clk $end
$var wire 2 5 count2_in [1:0] $end
$var wire 2 6 debug_count2_in [1:0] $end
$var wire 1 7 debug_sym_in $end
$var wire 1 8 disp_n $end
$var wire 1 , ld_out $end
$var wire 1 9 reset_n $end
$var wire 1 ' sym_in $end
$var wire 3 : size_in [2:0] $end
$var wire 3 ; debug_size_in [2:0] $end
$var wire 3 < debug_size_count [2:0] $end
$var wire 2 = array_1or3 [1:0] $end
$var reg 1 > debug_all_syms_procd $end
$var reg 1 / en_count_out $end
$var reg 1 . en_reg_out $end
$var reg 1 ? led_off_for_one_pulse $end
$var reg 1 @ led_out $end
$var reg 1 * reset_count_out $end
$var reg 3 A size_counter [2:0] $end
$upscope $end
$scope module half_sec $end
$var wire 1 B clk $end
$var wire 1 & reset_n $end
$var reg 25 C q [24:0] $end
$var reg 1 - rollover $end
$upscope $end
$scope module letter_logic $end
$var wire 3 D letter_in [2:0] $end
$var reg 4 E letter_out [3:0] $end
$var reg 3 F size [2:0] $end
$upscope $end
$scope module shift_reg $end
$var wire 1 ! clk $end
$var wire 4 G d [3:0] $end
$var wire 1 . en $end
$var wire 1 , ld $end
$var wire 1 H reset_n $end
$var wire 1 ' q $end
$var reg 4 I sr [3:0] $end
$upscope $end
$scope module size_reg $end
$var wire 1 ! clk $end
$var wire 3 J d [2:0] $end
$var wire 1 , ld $end
$var wire 1 K reset_n $end
$var reg 3 L q [2:0] $end
$upscope $end
$upscope $end
$upscope $end
$enddefinitions $end
#0
$dumpvars
bx L
1K
b10 J
bx I
1H
b100 G
b10 F
b100 E
b0 D
bx C
xB
bx A
x@
x?
x>
bx1 =
bx <
b0xx ;
bx :
19
18
x7
bx1 6
bx 5
x4
bx 3
x2
b0xxxxxx1xx 1
bx 0
x/
0.
x-
0,
b100 +
1*
b10 )
bx (
x'
1&
b0 %
b11 $
b0 #
b11 "
1!
$end
#2
02
0B
04
b0 ;
b0 0
b0 3
b0 5
0-
b0 C
0>
0?
b0 <
b0 A
0@
0*
0/
b1 6
b1 =
b100 1
07
0'
b0 (
b0 :
b0 L
b0 I
0&
0K
0H
09
b10 "
b10 $
#10
0!
#20
1!
#22
1K
1H
19
b11 "
b11 $
#30
0!
#40
1&
1*
1!
#42
1,
08
b1 "
b1 $
#50
0!
#60
0&
1B
b101 1
1@
0*
1/
b100 I
b10 (
b10 :
b10 L
1!
#62
0,
18
b11 "
b11 $
#70
0B
0!
#80
1&
1*
1B
1!
#90
0B
0!
#100
b1 C
1B
1!
#110
0B
0!
#120
b10 C
1B
1!
#130
0B
0!
#140
b11 C
1B
1!
#150
0B
0!
#160
b100 C
1B
1!
#170
0B
0!
#180
b101 C
1B
1!
#190
0B
0!
#200
b110 C
1B
1!
#210
0B
0!
#220
b111 C
1B
1!
#230
0B
0!
#240
b1000 C
1B
1!
#250
0B
0!
#260
b1001 C
1B
1!
#270
0B
0!
#280
b1010 C
1B
1!
#290
0B
0!
#300
b1011 C
1B
1!
#310
0B
0!
#320
b1100 C
1B
1!
#330
0B
0!
#340
b1101 C
1B
1!
#350
0B
0!
#360
b1110 C
1B
1!
#370
0B
0!
#380
b1111 C
1B
1!
#390
0B
0!
#400
b10000101 1
b1 ;
b1 0
b1 3
b1 5
12
1-
b0 C
1B
1!
#410
0B
0!
#420
b0 ;
b0 0
b0 3
b0 5
02
0&
0-
b0 C
1?
b1 <
b1 A
0*
1.
b10100 1
0@
1B
1!
#430
0B
0!
#440
1&
1*
0.
b11 6
b11 =
b11110 1
17
1'
1B
b1000 I
1!
#450
0B
0!
#460
b1 C
1B
1!
#470
0B
0!
#480
b10 C
1B
1!
#490
0B
0!
#500
b11 C
1B
1!
#510
0B
0!
#520
b100 C
1B
1!
#530
0B
0!
#540
b101 C
1B
1!
#550
0B
0!
#560
b110 C
1B
1!
#570
0B
0!
#580
b111 C
1B
1!
#590
0B
0!
#600
b1000 C
1B
1!
#610
0B
0!
#620
b1001 C
1B
1!
#630
0B
0!
#640
b1010 C
1B
1!
#650
0B
0!
#660
b1011 C
1B
1!
#670
0B
0!
#680
b1100 C
1B
1!
#690
0B
0!
#700
b1101 C
1B
1!
#710
0B
0!
#720
b1110 C
1B
1!
#730
0B
0!
#740
b1111 C
1B
1!
#750
0B
0!
#760
b10011110 1
b1 ;
b1 0
b1 3
b1 5
12
1-
b0 C
1B
1!
#770
0B
0!
#780
b0 ;
b0 0
b0 3
b0 5
02
0&
0-
b0 C
0*
b11111 1
1@
0?
1B
1!
#790
0B
0!
#800
1&
1*
1B
1!
#810
0B
0!
#820
b1 C
1B
1!
#830
0B
0!
#840
b10 C
1B
1!
#850
0B
0!
#860
b11 C
1B
1!
#870
0B
0!
#880
b100 C
1B
1!
#890
0B
0!
#900
b101 C
1B
1!
#910
0B
0!
#920
b110 C
1B
1!
#930
0B
0!
#940
b111 C
1B
1!
#950
0B
0!
#960
b1000 C
1B
1!
#970
0B
0!
#980
b1001 C
1B
1!
#990
0B
0!
#1000
b1010 C
1B
1!
#1010
0B
0!
#1020
b1011 C
1B
1!
#1030
0B
0!
#1040
b1100 C
1B
1!
#1050
0B
0!
#1060
b1101 C
1B
1!
#1070
0B
0!
#1080
b1110 C
1B
1!
#1090
0B
0!
#1100
b1111 C
1B
1!
#1110
0B
0!
#1120
b10011111 1
b1 ;
b1 0
b1 3
b1 5
12
1-
b0 C
1B
1!
#1130
0B
0!
#1140
02
0-
b1 C
1B
1!
#1150
0B
0!
#1160
b10 C
1B
1!
#1170
0B
0!
#1180
b11 C
1B
1!
#1190
0B
0!
#1200
b100 C
1B
1!
#1210
0B
0!
#1220
b101 C
1B
1!
#1230
0B
0!
#1240
b110 C
1B
1!
#1250
0B
0!
#1260
b111 C
1B
1!
#1270
0B
0!
#1280
b1000 C
1B
1!
#1290
0B
0!
#1300
b1001 C
1B
1!
#1310
0B
0!
#1320
b1010 C
1B
1!
#1330
0B
0!
#1340
b1011 C
1B
1!
#1350
0B
0!
#1360
b1100 C
1B
1!
#1370
0B
0!
#1380
b1101 C
1B
1!
#1390
0B
0!
#1400
b1110 C
1B
1!
#1410
0B
0!
#1420
b1111 C
1B
1!
#1430
0B
0!
#1440
b100011111 1
b10 ;
b10 0
b10 3
b10 5
12
1-
b0 C
1B
1!
#1450
0B
0!
#1460
02
0-
b1 C
1B
1!
#1470
0B
0!
#1480
b10 C
1B
1!
#1490
0B
0!
#1500
b11 C
1B
1!
#1510
0B
0!
#1520
b100 C
1B
1!
#1530
0B
0!
#1540
b101 C
1B
1!
#1550
0B
0!
#1560
b110 C
1B
1!
#1570
0B
0!
#1580
b111 C
1B
1!
#1590
0B
0!
#1600
b1000 C
1B
1!
#1610
0B
0!
#1620
b1001 C
1B
1!
#1630
0B
0!
#1640
b1010 C
1B
1!
#1650
0B
0!
#1660
b1011 C
1B
1!
#1670
0B
0!
#1680
b1100 C
1B
1!
#1690
0B
0!
#1700
b1101 C
1B
1!
#1710
0B
0!
#1720
b1110 C
1B
1!
#1730
0B
0!
#1740
b1111 C
1B
1!
#1750
0B
0!
#1760
b110011111 1
b11 ;
b11 0
b11 3
b11 5
12
1-
b0 C
1B
1!
#1770
0B
0!
#1780
b0 ;
b0 0
b0 3
b0 5
02
0&
0-
b0 C
1?
b10 <
b10 A
0*
1.
b101110 1
0@
1B
1!
#1790
0B
0!
#1800
1&
1*
0.
b1 6
b1 =
b100100 1
07
0'
1B
b0 I
1!
#1810
0B
0!
#1820
b1 C
1B
1!
#1830
0B
0!
#1840
b10 C
1B
1!
#1850
0B
0!
#1860
b11 C
1B
1!
#1870
0B
0!
#1880
b100 C
1B
1!
#1890
0B
0!
#1900
b101 C
1B
1!
#1910
0B
0!
#1920
b110 C
1B
1!
#1930
0B
0!
#1940
b111 C
1B
1!
#1950
0B
0!
#1960
b1000 C
1B
1!
#1970
0B
0!
#1980
b1001 C
1B
1!
#1990
0B
0!
#2000
b1010 C
1B
1!
#2010
0B
0!
#2020
b1011 C
1B
1!
#2030
0B
0!
#2040
b1100 C
1B
1!
#2050
0B
0!
#2060
b1101 C
1B
1!
#2070
0B
0!
#2080
b1110 C
1B
1!
#2090
0B
0!
#2100
b1111 C
1B
1!
#2110
0B
0!
#2120
b10100100 1
b1 ;
b1 0
b1 3
b1 5
12
1-
b0 C
1B
1!
#2130
0B
0!
#2140
b100100 1
b0 ;
b0 0
b0 3
b0 5
0&
02
0-
b0 C
1>
0*
0/
0B
1!
#2150
0!
#2160
1&
1*
1!
